[
    {
        "Previdenci\u00e1rio": {
            "(-) Valor Presente dos Benef\u00edcios Futuros (Aposentados)": {
                "2015": 0,
                "2016": 0,
                "2017": 0,
                "2018": 0,
                "2019": 0,
                "2020": -161552255,
                "2021": -138916587,
                "2022": -119584785
            },
            "(+) Valor Presente das Contribui\u00e7\u00f5es Futuras Participante (Aposentados)": {
                "2015": 0,
                "2016": 0,
                "2017": 0,
                "2018": 0,
                "2019": 0,
                "2020": 3150934,
                "2021": 3103507,
                "2022": 2369882
            },
            "(-) Valor Presente dos Benef\u00edcios Futuros (Pensionistas)": {
                "2015": 0,
                "2016": 0,
                "2017": 0,
                "2018": 0,
                "2019": -1173630,
                "2020": -48753302,
                "2021": -58794773,
                "2022": -63464835
            },
            "(+) Valor Presente das Contribui\u00e7\u00f5es Futuras Participante (Pensionistas)": {
                "2015": 0,
                "2016": 0,
                "2017": 0,
                "2018": 0,
                "2019": 0,
                "2020": 358617,
                "2021": 636844,
                "2022": 629648
            },
            "(+) Valor da Compensa\u00e7\u00e3o Previdenci\u00e1ria (Beneficios Concedidos)": {
                "2015": 0,
                "2016": 0,
                "2017": 0,
                "2018": 0,
                "2019": 0,
                "2020": 6466208,
                "2021": 5419785,
                "2022": 4449520
            },
            "(=) Reserva Matem\u00e1tica de Benef\u00edcios Concedidos (RMB - Concedidos)": {
                "2015": 0,
                "2016": 0,
                "2017": 0,
                "2018": 0,
                "2019": -1173630,
                "2020": -200329798,
                "2021": -188551223,
                "2022": -175600569
            },
            "(-) Valor Presente dos Benef\u00edcios Futuros (A Conceder)": {
                "2015": -511360,
                "2016": -171880775,
                "2017": -274470380,
                "2018": -363263194,
                "2019": -626309002,
                "2020": -880608602,
                "2021": -1076768369,
                "2022": -1071872233
            },
            "(+) Valor Presente das Contribui\u00e7\u00f5es Futuras Patrocinador": {
                "2015": 329371,
                "2016": 107893393,
                "2017": 167071366,
                "2018": 216797557,
                "2019": 368567071,
                "2020": 459071202,
                "2021": 609517380,
                "2022": 635696797
            },
            "(+) Valor Presente das Contribui\u00e7\u00f5es Futuras Participante": {
                "2015": 164686,
                "2016": 59341366,
                "2017": 91889251,
                "2018": 119238656,
                "2019": 202711889,
                "2020": 321349842,
                "2021": 342976018,
                "2022": 357707201
            },
            "(+) Valor da Compensa\u00e7\u00e3o Previdenci\u00e1ria (Beneficios a Conceder)": {
                "2015": 0,
                "2016": 0,
                "2017": 0,
                "2018": 0,
                "2019": 0,
                "2020": 0,
                "2021": 0,
                "2022": 0
            },
            "(=) Reserva Matem\u00e1tica de Benef\u00edcios a Conceder (RMB a Conceder)": {
                "2015": -17303,
                "2016": -4646016,
                "2017": -15509764,
                "2018": -27226980,
                "2019": -55030042,
                "2020": -100187559,
                "2021": -124274971,
                "2022": -78468235
            },
            "(=) Reserva Matem\u00e1tica (RMBC + RMBaC)": {
                "2015": -17303,
                "2016": -4646016,
                "2017": -15509764,
                "2018": -27226980,
                "2019": -56203672,
                "2020": -300517357,
                "2021": -312826194,
                "2022": -254068804
            },
            "(+) Valor Presente dos Acordos de Parcelamentos": {
                "2015": 0,
                "2016": 0,
                "2017": 0,
                "2018": 0,
                "2019": 0,
                "2020": 0,
                "2021": 0,
                "2022": 0
            },
            "(+) Ativo L\u00edquido do Plano": {
                "2015": 44951,
                "2016": 7638932,
                "2017": 27655647,
                "2018": 53975056,
                "2019": 93895495,
                "2020": 375844868,
                "2021": 395071601,
                "2022": 454318845
            },
            "(=) Ativo Total do Plano": {
                "2015": 44951,
                "2016": 7638932,
                "2017": 27655647,
                "2018": 53975056,
                "2019": 93895495,
                "2020": 375844868,
                "2021": 395071601,
                "2022": 454318845
            },
            "Resultado Atuarial": {
                "2015": 27648,
                "2016": 2992917,
                "2017": 12145883,
                "2018": 26748076,
                "2019": 37691823,
                "2020": 75327511,
                "2021": 82245407,
                "2022": 200250040
            }
        },
        "Financeiro": {
            "(-) Valor Presente dos Benef\u00edcios Futuros (Aposentados)": {
                "2015": -1612592577,
                "2016": -1661678250,
                "2017": -1919679095,
                "2018": -2559572897,
                "2019": -3037900111,
                "2020": -1544389565,
                "2021": -1726005756,
                "2022": -1862599026
            },
            "(+) Valor Presente das Contribui\u00e7\u00f5es Futuras Participante (Aposentados)": {
                "2015": 23800048,
                "2016": 23643822,
                "2017": 25147079,
                "2018": 33292215,
                "2019": 45063014,
                "2020": 24578724,
                "2021": 30218877,
                "2022": 33409593
            },
            "(-) Valor Presente dos Benef\u00edcios Futuros (Pensionistas)": {
                "2015": -455978645,
                "2016": -465577874,
                "2017": -493109460,
                "2018": -427846281,
                "2019": -491603223,
                "2020": -237550194,
                "2021": -277079075,
                "2022": -319906087
            },
            "(+) Valor Presente das Contribui\u00e7\u00f5es Futuras Participante (Pensionistas)": {
                "2015": 5288187,
                "2016": 4685278,
                "2017": 3931224,
                "2018": 3200936,
                "2019": 4063722,
                "2020": 2222715,
                "2021": 3039151,
                "2022": 4489724
            },
            "(+) Valor da Compensa\u00e7\u00e3o Previdenci\u00e1ria (Beneficios Concedidos)": {
                "2015": 0,
                "2016": 0,
                "2017": 0,
                "2018": 34253725,
                "2019": 58748469,
                "2020": 16039688,
                "2021": 14793404,
                "2022": 13803886
            },
            "(=) Reserva Matem\u00e1tica de Benef\u00edcios Concedidos (RMB - Concedidos)": {
                "2015": -2039482987,
                "2016": -2098927024,
                "2017": -2383710252,
                "2018": -2916672303,
                "2019": -3421628129,
                "2020": -1739098631,
                "2021": -1955033400,
                "2022": -2130801910
            },
            "(-) Valor Presente dos Benef\u00edcios Futuros (A Conceder)": {
                "2015": -3673193297,
                "2016": -3748507238,
                "2017": -3981479831,
                "2018": -4604519548,
                "2019": -5357271548,
                "2020": -3123542265,
                "2021": -3012877835,
                "2022": -2422621339
            },
            "(+) Valor Presente das Contribui\u00e7\u00f5es Futuras Patrocinador": {
                "2015": 846774022,
                "2016": 606601874,
                "2017": 601333884,
                "2018": 601136605,
                "2019": 516384042,
                "2020": 355867816,
                "2021": 336168371,
                "2022": 418687036
            },
            "(+) Valor Presente das Contribui\u00e7\u00f5es Futuras Participante": {
                "2015": 423387011,
                "2016": 333631031,
                "2017": 330733636,
                "2018": 330625133,
                "2019": 284011223,
                "2020": 249107471,
                "2021": 189162266,
                "2022": 235595599
            },
            "(+) Valor da Compensa\u00e7\u00e3o Previdenci\u00e1ria (Beneficios a Conceder)": {
                "2015": 408038384,
                "2016": 447515911,
                "2017": 473179943,
                "2018": 460451955,
                "2019": 535727155,
                "2020": 307016209,
                "2021": 271159005,
                "2022": 193809707
            },
            "(=) Reserva Matem\u00e1tica de Benef\u00edcios a Conceder (RMB a Conceder)": {
                "2015": -1994993880,
                "2016": -2360758423,
                "2017": -2576232369,
                "2018": -3212305855,
                "2019": -4021149128,
                "2020": -2211550769,
                "2021": -2216388193,
                "2022": -1574528997
            },
            "(=) Reserva Matem\u00e1tica (RMBC + RMBaC)": {
                "2015": -4034476868,
                "2016": -4459685447,
                "2017": -4959942621,
                "2018": -6128978158,
                "2019": -7442777258,
                "2020": -3950649400,
                "2021": -4171421592,
                "2022": -3705330907
            },
            "(+) Valor Presente dos Acordos de Parcelamentos": {
                "2015": 0,
                "2016": 0,
                "2017": 0,
                "2018": 0,
                "2019": 0,
                "2020": 0,
                "2021": 0,
                "2022": 0
            },
            "(+) Ativo L\u00edquido do Plano": {
                "2015": 197791067,
                "2016": 198358279,
                "2017": 194748474,
                "2018": 198121657,
                "2019": 218607062,
                "2020": 13286351,
                "2021": 35591428,
                "2022": 67384213
            },
            "(=) Ativo Total do Plano": {
                "2015": 197791067,
                "2016": 198358279,
                "2017": 194748474,
                "2018": 198121657,
                "2019": 218607062,
                "2020": 13286351,
                "2021": 35591428,
                "2022": 67384213
            },
            "Resultado Atuarial": {
                "2015": -3836685801,
                "2016": -4261327168,
                "2017": -4765194147,
                "2018": -5930856501,
                "2019": -7224170195,
                "2020": -3937363049,
                "2021": -4135830164,
                "2022": -3637946695
            }
        }
    }
]