[
        {
                "Previdenci\u00e1rio": {
                        "2015": {
                                "Feminino": [
                                        {
                                                "Servidores": 1164
                                        },
                                        {
                                                "Aposentados": 430
                                        },
                                        {
                                                "Pensionistas": 71
                                        },
                                        {
                                                "S. Iminentes": 84
                                        }
                                ],
                                "Masculino": [
                                        {
                                                "Servidores": 372
                                        },
                                        {
                                                "Aposentados": 132
                                        },
                                        {
                                                "Pensionistas": 29
                                        },
                                        {
                                                "S. Iminentes": 4
                                        }
                                ]
                        },
                        "2016": {
                                "Feminino": [
                                        {
                                                "Servidores": 1206
                                        },
                                        {
                                                "Aposentados": 450
                                        },
                                        {
                                                "Pensionistas": 76
                                        },
                                        {
                                                "S. Iminentes": 108
                                        }
                                ],
                                "Masculino": [
                                        {
                                                "Servidores": 391
                                        },
                                        {
                                                "Aposentados": 126
                                        },
                                        {
                                                "Pensionistas": 27
                                        },
                                        {
                                                "S. Iminentes": 5
                                        }
                                ]
                        },
                        "2017": {
                                "Feminino": [
                                        {
                                                "Servidores": 1190
                                        },
                                        {
                                                "Aposentados": 494
                                        },
                                        {
                                                "Pensionistas": 83
                                        },
                                        {
                                                "S. Iminentes": 120
                                        }
                                ],
                                "Masculino": [
                                        {
                                                "Servidores": 379
                                        },
                                        {
                                                "Aposentados": 125
                                        },
                                        {
                                                "Pensionistas": 27
                                        },
                                        {
                                                "S. Iminentes": 8
                                        }
                                ]
                        },
                        "2018": {
                                "Feminino": [
                                        {
                                                "Servidores": 1026
                                        },
                                        {
                                                "Aposentados": 576
                                        },
                                        {
                                                "Pensionistas": 85
                                        },
                                        {
                                                "S. Iminentes": 202
                                        }
                                ],
                                "Masculino": [
                                        {
                                                "Servidores": 314
                                        },
                                        {
                                                "Aposentados": 136
                                        },
                                        {
                                                "Pensionistas": 27
                                        },
                                        {
                                                "S. Iminentes": 63
                                        }
                                ]
                        },
                        "2019": {
                                "Feminino": [
                                        {
                                                "Servidores": 1174
                                        },
                                        {
                                                "Aposentados": 629
                                        },
                                        {
                                                "Pensionistas": 98
                                        },
                                        {
                                                "S. Iminentes": 95
                                        }
                                ],
                                "Masculino": [
                                        {
                                                "Servidores": 395
                                        },
                                        {
                                                "Aposentados": 142
                                        },
                                        {
                                                "Pensionistas": 27
                                        },
                                        {
                                                "S. Iminentes": 5
                                        }
                                ]
                        },
                        "2020": {
                                "Feminino": [
                                        {
                                                "Servidores": 1222
                                        },
                                        {
                                                "Aposentados": 678
                                        },
                                        {
                                                "Pensionistas": 103
                                        },
                                        {
                                                "S. Iminentes": 80
                                        }
                                ],
                                "Masculino": [
                                        {
                                                "Servidores": 405
                                        },
                                        {
                                                "Aposentados": 143
                                        },
                                        {
                                                "Pensionistas": 30
                                        },
                                        {
                                                "S. Iminentes": 7
                                        }
                                ]
                        },
                        "2021": {
                                "Feminino": [
                                        {
                                                "Servidores": 1152
                                        },
                                        {
                                                "S. Iminentes": 113
                                        },
                                        {
                                                "Aposentados": 711
                                        },
                                        {
                                                "Pensionistas": 99
                                        }
                                ],
                                "Masculino": [
                                        {
                                                "Servidores": 410
                                        },
                                        {
                                                "S. Iminentes": 11
                                        },
                                        {
                                                "Aposentados": 157
                                        },
                                        {
                                                "Pensionistas": 35
                                        }
                                ]
                        },
                        "2022": {
                                "Feminino": [
                                        {
                                                "Servidores": 1115
                                        },
                                        {
                                                "Aposentados": 740
                                        },
                                        {
                                                "Pensionistas": 104
                                        },
                                        {
                                                "S. Iminentes": 114
                                        }
                                ],
                                "Masculino": [
                                        {
                                                "Servidores": 402
                                        },
                                        {
                                                "Aposentados": 154
                                        },
                                        {
                                                "Pensionistas": 33
                                        },
                                        {
                                                "S. Iminentes": 20
                                        }
                                ]
                        }
                }
        }
]