[
        {
                "Previdenci\u00e1rio": {
                        "2017": {
                                "Feminino": [
                                        {
                                                "Aposentados": 75
                                        },
                                        {
                                                "Pensionistas": 18
                                        },
                                        {
                                                "Servidores": 213
                                        },
                                        {
                                                "Servidores Iminentes": 3
                                        }
                                ],
                                "Masculino": [
                                        {
                                                "Aposentados": 15
                                        },
                                        {
                                                "Pensionistas": 9
                                        },
                                        {
                                                "Servidores": 206
                                        },
                                        {
                                                "Servidores Iminentes": 1
                                        }
                                ]
                        },
                        "2018": {
                                "Feminino": [
                                        {
                                                "Aposentados": 78
                                        },
                                        {
                                                "Pensionistas": 19
                                        },
                                        {
                                                "Servidores": 210
                                        },
                                        {
                                                "Servidores Iminentes": 6
                                        }
                                ],
                                "Masculino": [
                                        {
                                                "Aposentados": 15
                                        },
                                        {
                                                "Pensionistas": 9
                                        },
                                        {
                                                "Servidores": 206
                                        },
                                        {
                                                "Servidores Iminentes": 1
                                        }
                                ]
                        },
                        "2019": {
                                "Feminino": [
                                        {
                                                "Servidores": 207
                                        },
                                        {
                                                "Aposentados": 78
                                        },
                                        {
                                                "Pensionistas": 19
                                        }
                                ],
                                "Masculino": [
                                        {
                                                "Servidores": 219
                                        },
                                        {
                                                "Aposentados": 15
                                        },
                                        {
                                                "Pensionistas": 9
                                        }
                                ]
                        }
                }
        }
]