[
   {
      "2015": {
         "Previdenci\u00e1rio": {
            "Servidores": 174,
            "Aposentados": 22,
            "Pensionistas": 5
         }
      },
      "2016": {
         "Previdenci\u00e1rio": {
            "Aposentados": 23,
            "Pensionistas": 5,
            "Servidores": 171
         }
      },
      "2017": {
         "Previdenci\u00e1rio": {
            "Aposentados": 28,
            "Pensionistas": 5,
            "Servidores": 159
         }
      },
      "2018": {
         "Previdenci\u00e1rio": {
            "Aposentados": 31,
            "Pensionistas": 5,
            "Servidores": 209
         }
      },
      "2019": {
         "Previdenci\u00e1rio": {
            "Aposentados": 34,
            "Pensionistas": 6,
            "Servidores": 210
         }
      },
      "2020": {
         "Previdenci\u00e1rio": {
            "Aposentados": 36,
            "Pensionistas": 9,
            "Servidores": 218
         }
      },
      "2021": {
         "Previdenci\u00e1rio": {
            "Aposentados": 38,
            "Pensionistas": 10,
            "Servidores": 212
         }
      },
      "2022": {
         "Previdenci\u00e1rio": {
            "Aposentados": 41,
            "Pensionistas": 10,
            "Servidores": 205
         }
      }
   }
]