[
   {
      "2015": {
         "Previdenci\u00e1rio": {
            "Aposentados": 19,
            "Pensionistas": 4,
            "Servidores": 113
         }
      },
      "2016": {
         "Previdenci\u00e1rio": {
            "Aposentados": 22,
            "Pensionistas": 10,
            "Servidores": 110
         }
      },
      "2017": {
         "Previdenci\u00e1rio": {
            "Aposentados": 25,
            "Pensionistas": 6,
            "Servidores": 163,
            "Servidores Iminentes": 4
         }
      },
      "2018": {
         "Previdenci\u00e1rio": {
            "Aposentados": 31,
            "Pensionistas": 8,
            "Servidores": 143,
            "Servidores Iminentes": 13
         }
      },
      "2019": {
         "Previdenci\u00e1rio": {
            "Aposentados": 42,
            "Servidores": 132,
            "Servidores Iminentes": 21
         }
      },
      "2020": {
         "Previdenci\u00e1rio": {
            "Aposentados": 58,
            "Pensionistas": 8,
            "Servidores": 119,
            "Servidores Iminentes": 14
         }
      }
   }
]